app/__init__.py
app/setup.py
app/setup_metrics.py
metrics_impetus-0.1.2.dist-info/METADATA
metrics_impetus-0.1.2.dist-info/WHEEL
metrics_impetus-0.1.2.dist-info/top_level.txt
metrics_impetus-0.1.2.dist-info/RECORD
